{
    "name": "act",
    "id": "act",
    "version": "1.1.0",
    "description": "Run your GitHub Actions locally 🚀",
    "options": {
        "version": {
            "type": "string",
            "proposals": [
                "latest",
                "0.2.64",
                "0.2.63",
                "0.2.62",
                "0.2.61",
                "0.2.60"
            ],
            "default": "latest",
            "description": "Select or enter a act version"
        }
    },
    "customizations": {
        "vscode": {
            "extensions": [
                "github.vscode-github-actions"
            ]
        }
    },
    "installsAfter": [
        "ghcr.io/devcontainers/features/common-utils",
        "ghcr.io/devcontainers/features/docker-in-docker"
    ]
}
